.gitignore
DEVELOP.rst
MANIFEST.in
README.rst
bootstrap.sh
buildout.cfg
requirements.txt
setup.py
collective/__init__.py
collective.js.datatables.egg-info/PKG-INFO
collective.js.datatables.egg-info/SOURCES.txt
collective.js.datatables.egg-info/dependency_links.txt
collective.js.datatables.egg-info/entry_points.txt
collective.js.datatables.egg-info/namespace_packages.txt
collective.js.datatables.egg-info/not-zip-safe
collective.js.datatables.egg-info/requires.txt
collective.js.datatables.egg-info/top_level.txt
collective/js/__init__.py
collective/js/datatables/__init__.py
collective/js/datatables/configure.zcml
collective/js/datatables/rebuild_i18n.sh
collective/js/datatables/surl.py
collective/js/datatables/testing.py
collective/js/datatables/upgrades.py
collective/js/datatables/upgrades.zcml
collective/js/datatables/example/__init__.py
collective/js/datatables/example/configure.zcml
collective/js/datatables/example/example.pt
collective/js/datatables/locales/collective.js.datatables.pot
collective/js/datatables/locales/de/LC_MESSAGES/collective.js.datatables.po
collective/js/datatables/locales/en/LC_MESSAGES/collective.js.datatables.po
collective/js/datatables/locales/es/LC_MESSAGES/collective.js.datatables.po
collective/js/datatables/locales/fi/LC_MESSAGES/collective.js.datatables.po
collective/js/datatables/locales/fr/LC_MESSAGES/collective.js.datatables.po
collective/js/datatables/locales/it/LC_MESSAGES/collective.js.datatables.po
collective/js/datatables/locales/lt/LC_MESSAGES/collective.js.datatables.po
collective/js/datatables/locales/nl/LC_MESSAGES/collective.js.datatables.po
collective/js/datatables/locales/zh_CN/LC_MESSAGES/collective.js.datatables.po
collective/js/datatables/profiles/plone4/cssregistry.xml
collective/js/datatables/profiles/plone4/jsregistry.xml
collective/js/datatables/profiles/plone4/metadata.xml
collective/js/datatables/profiles/plone5/metadata.xml
collective/js/datatables/profiles/plone5/registry.xml
collective/js/datatables/resources/Readme.txt
collective/js/datatables/resources/license-bsd.txt
collective/js/datatables/resources/license-gpl2.txt
collective/js/datatables/resources/package.json
collective/js/datatables/resources/extras/AutoFill/Readme.txt
collective/js/datatables/resources/extras/AutoFill/media/css/dataTables.autoFill.css
