Metadata-Version: 1.1
Name: collective.js.datatables
Version: 4.1.2
Summary: Plone Integration of jquery.dataTables plugin
Home-page: https://github.com/collective/collective.js.datatables
Author: JeanMichel FRANCOIS aka toutpt
Author-email: jeanmichel.francois@makina-corpus.com
License: GPL
Platform: UNKNOWN
Classifier: Framework :: Plone
Classifier: Framework :: Plone :: 4.0
Classifier: Framework :: Plone :: 4.1
Classifier: Framework :: Plone :: 4.2
Classifier: Framework :: Plone :: 4.3
Classifier: Framework :: Plone :: 5.0
Classifier: Framework :: Plone :: 5.1
Classifier: Programming Language :: Python
